anki_sm_2/__init__.py
anki_sm_2/anki_sm_2.py
anki_sm_2-0.1.2.dist-info/LICENSE
anki_sm_2-0.1.2.dist-info/METADATA
anki_sm_2-0.1.2.dist-info/WHEEL
anki_sm_2-0.1.2.dist-info/top_level.txt
anki_sm_2-0.1.2.dist-info/RECORD
