Metadata-Version: 2.1
Name: anki-sm-2
Version: 0.1.2
Summary: Anki SM-2 based spaced repetition scheduler
Author-email: Joshua Hamilton <hamiltonjoshuadavid@gmail.com>
License:                     GNU AFFERO GENERAL PUBLIC LICENSE
Project-URL: homepage, https://github.com/joshdavham/anki-sm-2
Keywords: anki,sm-2,spaced-repetition,flashcard
Classifier: Programming Language :: Python :: 3
Classifier: License :: OSI Approved :: GNU Affero General Public License v3
Classifier: Operating System :: OS Independent
Requires-Python: >=3.10
License-File: LICENSE
